<?xml version="1.0"?>
<!DOCTYPE benchmark PUBLIC "+//IDN sosy-lab.org//DTD BenchExec benchmark 1.18//EN" "https://www.sosy-lab.org/benchexec/benchmark-1.18.dtd">
<benchmark tool="tools.pikos" walltimelimit="14400 s" threads="1">
    <option name="-q"/>
    <option name="-w"/>
    <option name="--rm-db"/>
    <option name="--display-times">no</option>
    <option name="--display-summary">no</option>
    <option name="--progress">no</option>
    <option name="--inline-all"/>
    <option name="--proc">inter</option>
    <option name="--no-checks"/>
    <option name="--no-fixpoint-cache"/>
    <option name="--prec">mem</option>
    <option name="-d">interval</option>

    <rundefinition name="interval-base">
    </rundefinition>
    <rundefinition name="interval-cc2">
      <option name="--cc"/>
      <option name="-nt">2</option>
    </rundefinition>
    <rundefinition name="interval-cc4">
      <option name="--cc"/>
      <option name="-nt">4</option>
    </rundefinition>

    <tasks>
      <option name="-cs">0</option>
      <include>dummy.bc</include>
    </tasks>
    <tasks>
      <option name="-cs">0</option>
      <include>OSS/xscreensaver-5.42/carousel.bc</include>
    </tasks>
    <tasks>
      <option name="-cs">0</option>
      <include>OSS/xscreensaver-5.42/ccurve.bc</include>
    </tasks>
    <tasks>
      <option name="-cs">0</option>
      <include>OSS/xscreensaver-5.42/celtic.bc</include>
    </tasks>
    <tasks>
      <option name="-cs">0</option>
      <include>OSS/xscreensaver-5.42/circuit.bc</include>
    </tasks>
    <tasks>
      <option name="-cs">0</option>
      <include>OSS/xscreensaver-5.42/cityflow.bc</include>
    </tasks>
    <tasks>
      <option name="-cs">0</option>
      <include>OSS/xscreensaver-5.42/cloudlife.bc</include>
    </tasks>
    <tasks>
      <option name="-cs">0</option>
      <include>OSS/xscreensaver-5.42/companioncube.bc</include>
    </tasks>
    <tasks>
      <option name="-cs">0</option>
      <include>OSS/xscreensaver-5.42/compass.bc</include>
    </tasks>
    <tasks>
      <option name="-cs">0</option>
      <include>OSS/xscreensaver-5.42/coral.bc</include>
    </tasks>
    <tasks>
      <option name="-cs">0</option>
      <include>OSS/xscreensaver-5.42/crackberg.bc</include>
    </tasks>
    <tasks>
      <option name="-cs">0</option>
      <include>OSS/xscreensaver-5.42/crumbler.bc</include>
    </tasks>
    <tasks>
      <option name="-cs">0</option>
      <include>OSS/xscreensaver-5.42/crystal.bc</include>
    </tasks>
    <tasks>
      <option name="-cs">0</option>
      <include>OSS/xscreensaver-5.42/cube21.bc</include>
    </tasks>
    <tasks>
      <option name="-cs">0</option>
      <include>OSS/xscreensaver-5.42/cubenetic.bc</include>
    </tasks>
    <tasks>
      <option name="-cs">0</option>
      <include>OSS/xscreensaver-5.42/cubestack.bc</include>
    </tasks>
    <tasks>
      <option name="-cs">0</option>
      <include>OSS/xscreensaver-5.42/cubestorm.bc</include>
    </tasks>
    <tasks>
      <option name="-cs">0</option>
      <include>OSS/xscreensaver-5.42/cubetwist.bc</include>
    </tasks>
    <tasks>
      <option name="-cs">0</option>
      <include>OSS/xscreensaver-5.42/cubicgrid.bc</include>
    </tasks>
    <tasks>
      <option name="-cs">0</option>
      <include>OSS/xscreensaver-5.42/cwaves.bc</include>
    </tasks>
    <tasks>
      <option name="-cs">0</option>
      <include>OSS/xscreensaver-5.42/cynosure.bc</include>
    </tasks>
    <tasks>
      <option name="-cs">0</option>
      <include>OSS/xscreensaver-5.42/dangerball.bc</include>
    </tasks>
    <tasks>
      <option name="-cs">0</option>
      <include>OSS/xscreensaver-5.42/decayscreen.bc</include>
    </tasks>
</benchmark>
