<?xml version="1.0"?>
<!DOCTYPE benchmark PUBLIC "+//IDN sosy-lab.org//DTD BenchExec benchmark 1.18//EN" "https://www.sosy-lab.org/benchexec/benchmark-1.18.dtd">
<benchmark tool="tools.pikos" walltimelimit="14400 s" threads="1">
    <option name="-q"/>
    <option name="-w"/>
    <option name="--rm-db"/>
    <option name="--display-times">no</option>
    <option name="--display-summary">no</option>
    <option name="--progress">no</option>
    <option name="--inline-all"/>
    <option name="--proc">inter</option>
    <option name="--no-checks"/>
    <option name="--no-fixpoint-cache"/>
    <option name="--prec">mem</option>
    <option name="-d">interval</option>

    <rundefinition name="interval-base">
    </rundefinition>
    <rundefinition name="interval-cc2">
      <option name="--cc"/>
      <option name="-nt">2</option>
    </rundefinition>
    <rundefinition name="interval-cc4">
      <option name="--cc"/>
      <option name="-nt">4</option>
    </rundefinition>

    <tasks>
      <option name="-cs">0</option>
      <include>dummy.bc</include>
    </tasks>
    <tasks>
      <option name="-cs">0</option>
      <include>OSS/mtpfs-1.1/mtpfs.bc</include>
    </tasks>
    <tasks>
      <option name="-cs">0</option>
      <include>OSS/mtr-0.92/mtr.bc</include>
    </tasks>
    <tasks>
      <option name="-cs">0</option>
      <include>OSS/mtr-0.92/mtr-packet.bc</include>
    </tasks>
    <tasks>
      <option name="-cs">0</option>
      <include>OSS/musepack-0.1+r475/mpc2sv8.bc</include>
    </tasks>
    <tasks>
      <option name="-cs">0</option>
      <include>OSS/musepack-0.1+r475/mpcchap.bc</include>
    </tasks>
    <tasks>
      <option name="-cs">0</option>
      <include>OSS/musepack-0.1+r475/mpccut.bc</include>
    </tasks>
    <tasks>
      <option name="-cs">0</option>
      <include>OSS/musepack-0.1+r475/mpcdec.bc</include>
    </tasks>
    <tasks>
      <option name="-cs">0</option>
      <include>OSS/musepack-0.1+r475/mpcenc.bc</include>
    </tasks>
    <tasks>
      <option name="-cs">0</option>
      <include>OSS/musepack-0.1+r475/mpcgain.bc</include>
    </tasks>
    <tasks>
      <option name="-cs">0</option>
      <include>OSS/musepack-0.1+r475/wavcmp.bc</include>
    </tasks>
    <tasks>
      <option name="-cs">0</option>
      <include>OSS/mutt-1.11.4/mutt_pgpring.bc</include>
    </tasks>
    <tasks>
      <option name="-cs">0</option>
      <include>OSS/mutt-1.11.4/pgpewrap.bc</include>
    </tasks>
    <tasks>
      <option name="-cs">0</option>
      <include>OSS/mx-1.4.7+13+g24efb0cc/mx-create-image-cache.bc</include>
    </tasks>
    <tasks>
      <option name="-cs">13</option>
      <include>OSS/naev-0.7.0/naev.bc</include>
    </tasks>
    <tasks>
      <option name="-cs">11</option>
      <include>OSS/naim/naim.bc</include>
    </tasks>
    <tasks>
      <option name="-cs">0</option>
      <include>OSS/namazu-2.0.21/namazu.bc</include>
    </tasks>
    <tasks>
      <option name="-cs">0</option>
      <include>OSS/namazu-2.0.21/namazu.cgi.bc</include>
    </tasks>
    <tasks>
      <option name="-cs">13</option>
      <include>OSS/nano-4.1/nano.bc</include>
    </tasks>
    <tasks>
      <option name="-cs">0</option>
      <include>OSS/nanomsg-1.1.5/nanocat.bc</include>
    </tasks>
    <tasks>
      <option name="-cs">0</option>
      <include>OSS/nasm-2.14.02/ldrdf.bc</include>
    </tasks>
    <tasks>
      <option name="-cs">12</option>
      <include>OSS/nasm-2.14.02/nasm.bc</include>
    </tasks>
    <tasks>
      <option name="-cs">0</option>
      <include>OSS/nasm-2.14.02/ndisasm.bc</include>
    </tasks>
</benchmark>
